s2super/__init__.py
s2super/super_sample.py
s2super/train.py
s2super/train_utils.py
s2super/utils.py
s2super/s2super_v5/keras_metadata.pb
s2super/s2super_v5/saved_model.pb
s2super/s2super_v5/variables/variables.data-00000-of-00001
s2super/s2super_v5/variables/variables.index
s2super-1.2.30.dist-info/LICENSE
s2super-1.2.30.dist-info/WHEEL
s2super-1.2.30.dist-info/METADATA
s2super-1.2.30.dist-info/RECORD
