Metadata-Version: 2.1
Name: s2super
Version: 1.2.30
Summary: SuperResolution of Sentinel2 imagery.
Author-email: Casper Fibaek <casperfibaek@gmail.com>
Requires-Python: >=3.7
Classifier: Programming Language :: Python :: 3
Classifier: License :: OSI Approved :: MIT License
Classifier: Operating System :: OS Independent
Requires-Dist: tensorflow>=2.8
Requires-Dist: buteo>=0.7.65
Project-URL: Bug Tracker, https://github.com/casperfibaek/super_res_s2/issues
Project-URL: Homepage, https://github.com/casperfibaek/super_res_s2
